pushover.py
pushover_package/__init__.py
pushover_package-0.3.dist-info/METADATA
pushover_package-0.3.dist-info/WHEEL
pushover_package-0.3.dist-info/top_level.txt
pushover_package-0.3.dist-info/RECORD
