Metadata-Version: 2.1
Name: pushover-package
Version: 0.3
Summary: A simple Python wrapper for the Pushover API
Keywords: pushover notification api
Requires-Dist: requests
